kalifast.py
kalifast-0.1.71.dist-info/WHEEL
kalifast-0.1.71.dist-info/METADATA
kalifast-0.1.71.dist-info/RECORD
