Metadata-Version: 2.1
Name: kalifast
Version: 0.1.71
Summary: Python package for kalifast record npp plugin
Author-email: EISGE <e@eisge.com>
Requires-Dist: validators
Requires-Dist: pyautogui
Requires-Dist: opencv-python
Requires-Dist: pytesseract
